sunzip/__init__.py
sunzip/cli.py
sunzip-0.0.5.dist-info/LICENSE
sunzip-0.0.5.dist-info/METADATA
sunzip-0.0.5.dist-info/WHEEL
sunzip-0.0.5.dist-info/entry_points.txt
sunzip-0.0.5.dist-info/top_level.txt
sunzip-0.0.5.dist-info/RECORD
