Metadata-Version: 2.1
Name: sunzip
Version: 0.0.5
Summary: Provide secure unzip against zip bomb.
Home-page: https://github.com/twbgc/sunzip
Author: JunWeiSong,KunYuChen
Author-email: sungboss2004@gmail.com
License: UNKNOWN
Keywords: secure unzip,zipbomb
Platform: UNKNOWN
Classifier: Programming Language :: Python :: 3
Classifier: License :: OSI Approved :: GNU Lesser General Public License v3 (LGPLv3)
Classifier: Operating System :: OS Independent
